svgfont/__init__.py
svgfont/svgfont.py
svgfont-0.1.5.dist-info/licenses/LICENSE
svgfont-0.1.5.dist-info/METADATA
svgfont-0.1.5.dist-info/WHEEL
svgfont-0.1.5.dist-info/top_level.txt
svgfont-0.1.5.dist-info/RECORD
