Metadata-Version: 2.4
Name: svgfont
Version: 0.1.5
Summary: Load svg fonts
Author: Daniel Berio
License: MIT License
Project-URL: Homepage, https://github.com/colormotor/svgfont
Project-URL: Issues, https://github.com/colormotor/svgfont/issues
Requires-Python: >=3.9
License-File: LICENSE
Requires-Dist: numpy
Requires-Dist: svgpathtools
Dynamic: license-file
